asse/__init__.py
asse/usercustomize.py
asse-1.0.0.dist-info/METADATA
asse-1.0.0.dist-info/WHEEL
asse-1.0.0.dist-info/top_level.txt
asse-1.0.0.dist-info/RECORD
